unholy/__init__.py
unholy/__main__.py
unholy/compose.py
unholy/config.py
unholy/core.Unholyfile
unholy/docker.py
unholy/git.py
unholy/junk_drawer.py
unholy/processes.py
unholy-0.2.1.dist-info/METADATA
unholy-0.2.1.dist-info/WHEEL
unholy-0.2.1.dist-info/entry_points.txt
unholy-0.2.1.dist-info/RECORD
