Metadata-Version: 2.1
Name: unholy
Version: 0.2.1
Summary: The melding of docker compose and neovim
Home-page: https://github.com/AstraLuma/unholy
License: GPL-3
Author: Jamie Bliss
Author-email: jamie@ivyleav.es
Requires-Python: >3.10
Classifier: License :: Other/Proprietary License
Classifier: Programming Language :: Python :: 3
Classifier: Programming Language :: Python :: 3.11
Classifier: Programming Language :: Python :: 3.12
Requires-Dist: appdirs (>=1.4.4,<2.0.0)
Requires-Dist: click (>=8.1.3,<9.0.0)
Requires-Dist: docker[ssh,websockets] (>=6.1.3,<7.0.0)
Requires-Dist: tomlkit (>=0.12.2,<0.13.0)
Project-URL: Repository, https://github.com/AstraLuma/unholy
